{"cameraMode":{"drawMode":0,"name":"Shaded","section":"Shading Mode"},"sceneLighting":true,"audioPlay":false,"sceneViewState":{"m_AlwaysRefresh":false,"showFog":true,"showSkybox":true,"showFlares":true,"showImageEffects":true,"showParticleSystems":true,"showVisualEffectGraphs":true,"m_FxEnabled":true},"in2DMode":false,"pivot":{"x":951.066162109375,"y":542.3046875,"z":3.7781982421875},"rotation":{"x":-0.014999285340309143,"y":0.0044994777999818329,"z":0.00006749722524546087,"w":0.9998773336410523},"size":675.2327880859375,"orthographic":true}